[
    {
        "f_id": 182612,
        "name": "ป๊อปคอนรสออริจินัล1",
        "pic_id": 103919,
        "price": 120,
        "detail": "",
        "no_cook": "0",
        "sort": 0,
        "code_sale": "",
        "status": 2,
        "is_buffet": 0,
        "details": [],
        "code": "a103",
        "zone": [],
        "f_group": "12219",
        "toppings": [],
        "bg_id": [],
        "cooks": [
            "4875"
        ],
        "set_price_on_sale": "0",
        "pic_url": "https://deltafoodpicture.sgp1.digitaloceanspaces.com/foods/1700204488213565.jpg"
    },
    {
        "f_id": 174764,
        "name": "ข้าวโพดเบรคแตก",
        "pic_id": 103895,
        "price": 99,
        "detail": "",
        "no_cook": "0",
        "sort": 1,
        "code_sale": "",
        "status": 2,
        "is_buffet": 0,
        "details": [],
        "code": "a001",
        "zone": [],
        "f_group": "12219",
        "toppings": [],
        "bg_id": [],
        "cooks": [
            "4875"
        ],
        "set_price_on_sale": "0",
        "pic_url": "https://deltafoodpicture.sgp1.digitaloceanspaces.com/foods/1700202972263917.jpg"
    },
    {
        "f_id": 174765,
        "name": "แกล้มเดอะแบงค์",
        "pic_id": 103867,
        "price": 219,
        "detail": "ไม่ทราบ",
        "no_cook": "0",
        "sort": 2,
        "code_sale": "",
        "status": 2,
        "is_buffet": 0,
        "details": [],
        "code": "a002",
        "zone": [],
        "f_group": "12219",
        "toppings": [],
        "bg_id": [],
        "cooks": [
            "4875"
        ],
        "set_price_on_sale": "0",
        "pic_url": "https://deltafoodpicture.sgp1.digitaloceanspaces.com/foods/1700202024229252.jpg"
    },
    {
        "f_id": 174766,
        "name": "หมูคาราเมล",
        "pic_id": 103868,
        "price": 249,
        "detail": "ไม่ทราบ",
        "no_cook": "0",
        "sort": 3,
        "code_sale": "",
        "status": 2,
        "is_buffet": 0,
        "details": [],
        "code": "a003",
        "zone": [],
        "f_group": "12219",
        "toppings": [],
        "bg_id": [],
        "cooks": [
            "4875"
        ],
        "set_price_on_sale": "0",
        "pic_url": "https://deltafoodpicture.sgp1.digitaloceanspaces.com/foods/1700202355215640.jpg"
    },
    {
        "f_id": 174767,
        "name": "เนื้อฉ่ำไฟ",
        "pic_id": 103866,
        "price": 299,
        "detail": "ไม่ทราบ",
        "no_cook": "0",
        "sort": 4,
        "code_sale": "",
        "status": 2,
        "is_buffet": 0,
        "details": [],
        "code": "a004",
        "zone": [],
        "f_group": "12219",
        "toppings": [],
        "bg_id": [],
        "cooks": [
            "4875"
        ],
        "set_price_on_sale": "0",
        "pic_url": "https://deltafoodpicture.sgp1.digitaloceanspaces.com/foods/1700201882458625.jpg"
    },
    {
        "f_id": 174768,
        "name": "ข้าวผัดกะเพราเนื้อ ดรายเอจ ราดข้าว",
        "pic_id": 103870,
        "price": 149,
        "detail": "ไม่ทราบ",
        "no_cook": "0",
        "sort": 5,
        "code_sale": "",
        "status": 2,
        "is_buffet": 0,
        "details": [],
        "code": "a005",
        "zone": [],
        "f_group": "12219",
        "toppings": [],
        "bg_id": [],
        "cooks": [
            "4875"
        ],
        "set_price_on_sale": "0",
        "pic_url": "https://deltafoodpicture.sgp1.digitaloceanspaces.com/foods/1700202603208184.jpg"
    },
    {
        "f_id": 174769,
        "name": "เสือร้องไห้ไทยวากิว ",
        "pic_id": 103901,
        "price": 349,
        "detail": "ไม่ทราบ",
        "no_cook": "0",
        "sort": 6,
        "code_sale": "",
        "status": 2,
        "is_buffet": 0,
        "details": [],
        "code": "\t a006",
        "zone": [],
        "f_group": "12219",
        "toppings": [],
        "bg_id": [],
        "cooks": [
            "4875"
        ],
        "set_price_on_sale": "0",
        "pic_url": "https://deltafoodpicture.sgp1.digitaloceanspaces.com/foods/1700203835230144.jpg"
    },
    {
        "f_id": 174770,
        "name": "ขาหมูเยอรมัน",
        "pic_id": 103917,
        "price": 499,
        "detail": "ไม่ทราบ",
        "no_cook": "0",
        "sort": 7,
        "code_sale": "",
        "status": 2,
        "is_buffet": 0,
        "details": [],
        "code": "\t a007",
        "zone": [],
        "f_group": "12219",
        "toppings": [],
        "bg_id": [],
        "cooks": [
            "4875"
        ],
        "set_price_on_sale": "0",
        "pic_url": "https://deltafoodpicture.sgp1.digitaloceanspaces.com/foods/1700204334189663.jpg"
    },
    {
        "f_id": 174773,
        "name": "กะหล่ำผัดน้ำปลา",
        "pic_id": 103921,
        "price": 120,
        "detail": "ไม่ทราบ",
        "no_cook": "0",
        "sort": 9,
        "code_sale": "",
        "status": 2,
        "is_buffet": 0,
        "details": [],
        "code": "\t a009",
        "zone": [],
        "f_group": "12219",
        "toppings": [],
        "bg_id": [],
        "cooks": [
            "4875"
        ],
        "set_price_on_sale": "0",
        "pic_url": "https://deltafoodpicture.sgp1.digitaloceanspaces.com/foods/170020495065206.jpg"
    },
    {
        "f_id": 174776,
        "name": "ผัดกะเพรา หมู",
        "pic_id": 104122,
        "price": 120,
        "detail": "ไม่ทราบ",
        "no_cook": "0",
        "sort": 10,
        "code_sale": "",
        "status": 2,
        "is_buffet": 0,
        "details": [],
        "code": " a010",
        "zone": [],
        "f_group": "12219",
        "toppings": [],
        "bg_id": [],
        "cooks": [
            "4875"
        ],
        "set_price_on_sale": "0",
        "pic_url": "https://deltafoodpicture.sgp1.digitaloceanspaces.com/foods/170028983868846.jpg"
    },
    {
        "f_id": 174778,
        "name": "ผัดกะเพรา เนื้อ",
        "pic_id": 104747,
        "price": 150,
        "detail": "ไม่ทราบ",
        "no_cook": "0",
        "sort": 11,
        "code_sale": "",
        "status": 2,
        "is_buffet": 0,
        "details": [],
        "code": "a011",
        "zone": [],
        "f_group": "12219",
        "toppings": [],
        "bg_id": [],
        "cooks": [
            "4875"
        ],
        "set_price_on_sale": "0",
        "pic_url": "https://deltafoodpicture.sgp1.digitaloceanspaces.com/foods/1700714468119329.jpg"
    },
    {
        "f_id": 174781,
        "name": "หมูกรอบคั่วพริกเกลือ",
        "pic_id": 103914,
        "price": 150,
        "detail": "ไม่ทราบ",
        "no_cook": "0",
        "sort": 12,
        "code_sale": "",
        "status": 2,
        "is_buffet": 0,
        "details": [],
        "code": "\t a012",
        "zone": [],
        "f_group": "12219",
        "toppings": [],
        "bg_id": [],
        "cooks": [
            "4875"
        ],
        "set_price_on_sale": "0",
        "pic_url": "https://deltafoodpicture.sgp1.digitaloceanspaces.com/foods/1700204059247729.jpg"
    },
    {
        "f_id": 174783,
        "name": "ปลาหมึกผัดใข่เค็ม",
        "pic_id": 103898,
        "price": 150,
        "detail": "ไม่ทราบ",
        "no_cook": "0",
        "sort": 13,
        "code_sale": "",
        "status": 2,
        "is_buffet": 0,
        "details": [],
        "code": "\t a013",
        "zone": [],
        "f_group": "12219",
        "toppings": [],
        "bg_id": [],
        "cooks": [
            "4875"
        ],
        "set_price_on_sale": "0",
        "pic_url": "https://deltafoodpicture.sgp1.digitaloceanspaces.com/foods/1700203258178411.jpg"
    },
    {
        "f_id": 174785,
        "name": "ไก่ผัดเม็ดมะม่วง",
        "pic_id": 103904,
        "price": 120,
        "detail": "ไม่ทราบ",
        "no_cook": "0",
        "sort": 14,
        "code_sale": "",
        "status": 2,
        "is_buffet": 0,
        "details": [],
        "code": "\t a014",
        "zone": [],
        "f_group": "12219",
        "toppings": [],
        "bg_id": [],
        "cooks": [
            "4875"
        ],
        "set_price_on_sale": "0",
        "pic_url": "https://deltafoodpicture.sgp1.digitaloceanspaces.com/foods/1700203925212480.jpg"
    },
    {
        "f_id": 174787,
        "name": "ไก่รวนปลาร้า",
        "pic_id": 104123,
        "price": 120,
        "detail": "ไม่ทราบ",
        "no_cook": "0",
        "sort": 15,
        "code_sale": "",
        "status": 2,
        "is_buffet": 0,
        "details": [],
        "code": "\t a015",
        "zone": [],
        "f_group": "12219",
        "toppings": [],
        "bg_id": [],
        "cooks": [
            "4875"
        ],
        "set_price_on_sale": "0",
        "pic_url": "https://deltafoodpicture.sgp1.digitaloceanspaces.com/foods/170029016594738.jpg"
    },
    {
        "f_id": 174789,
        "name": "ผัดเผ็ดไก่บ้าน",
        "pic_id": 104124,
        "price": 120,
        "detail": "ไม่ทราบ",
        "no_cook": "0",
        "sort": 16,
        "code_sale": "",
        "status": 2,
        "is_buffet": 0,
        "details": [],
        "code": "\t a016",
        "zone": [],
        "f_group": "12219",
        "toppings": [],
        "bg_id": [],
        "cooks": [
            "4875"
        ],
        "set_price_on_sale": "0",
        "pic_url": "https://deltafoodpicture.sgp1.digitaloceanspaces.com/foods/170029022516245.jpg"
    },
    {
        "f_id": 174791,
        "name": "ผัดคะน้าหมูกรอบ",
        "pic_id": 104125,
        "price": 120,
        "detail": "ไม่ทราบ",
        "no_cook": "0",
        "sort": 17,
        "code_sale": "",
        "status": 2,
        "is_buffet": 0,
        "details": [],
        "code": "\t a017",
        "zone": [],
        "f_group": "12219",
        "toppings": [],
        "bg_id": [],
        "cooks": [
            "4875"
        ],
        "set_price_on_sale": "0",
        "pic_url": "https://deltafoodpicture.sgp1.digitaloceanspaces.com/foods/1700290342548617.jpg"
    },
    {
        "f_id": 174795,
        "name": "ปูอัดทอด",
        "pic_id": 103896,
        "price": 120,
        "detail": "ไม่ทราบ",
        "no_cook": "0",
        "sort": 18,
        "code_sale": "",
        "status": 2,
        "is_buffet": 0,
        "details": [],
        "code": "\t a018",
        "zone": [],
        "f_group": "12219",
        "toppings": [],
        "bg_id": [],
        "cooks": [
            "4875"
        ],
        "set_price_on_sale": "0",
        "pic_url": "https://deltafoodpicture.sgp1.digitaloceanspaces.com/foods/1700203034274320.jpg"
    },
    {
        "f_id": 174797,
        "name": "ทาโร่ทอด",
        "pic_id": 103918,
        "price": 100,
        "detail": "ไม่ทราบ",
        "no_cook": "0",
        "sort": 19,
        "code_sale": "",
        "status": 2,
        "is_buffet": 0,
        "details": [],
        "code": "\t a019",
        "zone": [],
        "f_group": "12219",
        "toppings": [],
        "bg_id": [],
        "cooks": [
            "4875"
        ],
        "set_price_on_sale": "0",
        "pic_url": "https://deltafoodpicture.sgp1.digitaloceanspaces.com/foods/1700204407258035.jpg"
    },
    {
        "f_id": 174799,
        "name": "ไส้กรอกโรงเรียน",
        "pic_id": 104155,
        "price": 100,
        "detail": "ไม่ทราบ",
        "no_cook": "0",
        "sort": 20,
        "code_sale": "",
        "status": 2,
        "is_buffet": 0,
        "details": [],
        "code": "\t a020",
        "zone": [],
        "f_group": "12219",
        "toppings": [],
        "bg_id": [],
        "cooks": [
            "4875"
        ],
        "set_price_on_sale": "0",
        "pic_url": "https://deltafoodpicture.sgp1.digitaloceanspaces.com/foods/1700294269189530.jpg"
    },
    {
        "f_id": 174800,
        "name": "เฟรนซ์ฟรายส์",
        "pic_id": 103858,
        "price": 120,
        "detail": "ไม่ทราบ",
        "no_cook": "0",
        "sort": 21,
        "code_sale": "",
        "status": 2,
        "is_buffet": 0,
        "details": [],
        "code": "\t a021",
        "zone": [],
        "f_group": "12219",
        "toppings": [],
        "bg_id": [],
        "cooks": [
            "4875"
        ],
        "set_price_on_sale": "0",
        "pic_url": "https://deltafoodpicture.sgp1.digitaloceanspaces.com/foods/1700200390110509.jpg"
    },
    {
        "f_id": 174803,
        "name": "ถั่วแระญี่ปุ่น",
        "pic_id": 104064,
        "price": 120,
        "detail": "ไม่ทราบ",
        "no_cook": "0",
        "sort": 22,
        "code_sale": "",
        "status": 2,
        "is_buffet": 0,
        "details": [],
        "code": "\t a022",
        "zone": [],
        "f_group": "12219",
        "toppings": [],
        "bg_id": [],
        "cooks": [
            "4875"
        ],
        "set_price_on_sale": "0",
        "pic_url": "https://deltafoodpicture.sgp1.digitaloceanspaces.com/foods/1700282443135250.jpg"
    },
    {
        "f_id": 174804,
        "name": "สัปปะรด ชีส",
        "pic_id": 103887,
        "price": 120,
        "detail": "ไม่ทราบ",
        "no_cook": "0",
        "sort": 23,
        "code_sale": "",
        "status": 2,
        "is_buffet": 0,
        "details": [],
        "code": "\t a023",
        "zone": [],
        "f_group": "12219",
        "toppings": [],
        "bg_id": [],
        "cooks": [
            "4875"
        ],
        "set_price_on_sale": "0",
        "pic_url": "https://deltafoodpicture.sgp1.digitaloceanspaces.com/foods/1700202882158248.jpg"
    },
    {
        "f_id": 174805,
        "name": "เม็ดมะม่วงทอด/ยำ",
        "pic_id": 104065,
        "price": 120,
        "detail": "ไม่ทราบ",
        "no_cook": "0",
        "sort": 24,
        "code_sale": "",
        "status": 2,
        "is_buffet": 0,
        "details": [],
        "code": "\t a024",
        "zone": [],
        "f_group": "12219",
        "toppings": [],
        "bg_id": [],
        "cooks": [
            "4875"
        ],
        "set_price_on_sale": "0",
        "pic_url": "https://deltafoodpicture.sgp1.digitaloceanspaces.com/foods/170028260578042.jpg"
    },
    {
        "f_id": 174806,
        "name": "หมึกวาซาบิ",
        "pic_id": 104126,
        "price": 100,
        "detail": "ไม่ทราบ",
        "no_cook": "0",
        "sort": 25,
        "code_sale": "",
        "status": 2,
        "is_buffet": 0,
        "details": [],
        "code": "\t a025",
        "zone": [],
        "f_group": "12219",
        "toppings": [],
        "bg_id": [],
        "cooks": [
            "4875"
        ],
        "set_price_on_sale": "0",
        "pic_url": "https://deltafoodpicture.sgp1.digitaloceanspaces.com/foods/1700290480207504.jpg"
    },
    {
        "f_id": 174807,
        "name": "นักเก็ต",
        "pic_id": 104121,
        "price": 100,
        "detail": "ไม่ทราบ",
        "no_cook": "0",
        "sort": 26,
        "code_sale": "",
        "status": 2,
        "is_buffet": 0,
        "details": [],
        "code": "\t a026",
        "zone": [],
        "f_group": "12219",
        "toppings": [],
        "bg_id": [],
        "cooks": [
            "4875"
        ],
        "set_price_on_sale": "0",
        "pic_url": "https://deltafoodpicture.sgp1.digitaloceanspaces.com/foods/170028978853918.jpg"
    },
    {
        "f_id": 174808,
        "name": "ป๊อปคอร์นรสคาราเมล",
        "pic_id": 103919,
        "price": 120,
        "detail": "ไม่ทราบ",
        "no_cook": "0",
        "sort": 27,
        "code_sale": "",
        "status": 2,
        "is_buffet": 0,
        "details": [],
        "code": "\t a027",
        "zone": [],
        "f_group": "12219",
        "toppings": [],
        "bg_id": [],
        "cooks": [
            "4875"
        ],
        "set_price_on_sale": "0",
        "pic_url": "https://deltafoodpicture.sgp1.digitaloceanspaces.com/foods/1700204488213565.jpg"
    },
    {
        "f_id": 174809,
        "name": "ต้มจืดเต้าหู้หมูสับ",
        "pic_id": 104127,
        "price": 120,
        "detail": "ไม่ทราบ",
        "no_cook": "0",
        "sort": 28,
        "code_sale": "",
        "status": 2,
        "is_buffet": 0,
        "details": [],
        "code": "\t a028",
        "zone": [],
        "f_group": "12219",
        "toppings": [],
        "bg_id": [],
        "cooks": [
            "4875"
        ],
        "set_price_on_sale": "0",
        "pic_url": "https://deltafoodpicture.sgp1.digitaloceanspaces.com/foods/1700290548228691.jpg"
    },
    {
        "f_id": 174810,
        "name": "ต้มซุปเปอร์ซี่โครง",
        "pic_id": 104128,
        "price": 120,
        "detail": "ไม่ทราบ",
        "no_cook": "0",
        "sort": 29,
        "code_sale": "",
        "status": 2,
        "is_buffet": 0,
        "details": [],
        "code": "\t a029",
        "zone": [],
        "f_group": "12219",
        "toppings": [],
        "bg_id": [],
        "cooks": [
            "4875"
        ],
        "set_price_on_sale": "0",
        "pic_url": "https://deltafoodpicture.sgp1.digitaloceanspaces.com/foods/170029062341057.jpg"
    },
    {
        "f_id": 174811,
        "name": "ต้มยำทะเล",
        "pic_id": 104131,
        "price": 190,
        "detail": "ไม่ทราบ",
        "no_cook": "0",
        "sort": 30,
        "code_sale": "",
        "status": 2,
        "is_buffet": 0,
        "details": [],
        "code": "\t a030",
        "zone": [],
        "f_group": "12219",
        "toppings": [],
        "bg_id": [],
        "cooks": [
            "4875"
        ],
        "set_price_on_sale": "0",
        "pic_url": "https://deltafoodpicture.sgp1.digitaloceanspaces.com/foods/1700291003151010.jpg"
    },
    {
        "f_id": 174812,
        "name": "ต้มยำรวมมิตร",
        "pic_id": 104131,
        "price": 150,
        "detail": "ไม่ทราบ",
        "no_cook": "0",
        "sort": 31,
        "code_sale": "",
        "status": 2,
        "is_buffet": 0,
        "details": [],
        "code": "\t a031",
        "zone": [],
        "f_group": "12219",
        "toppings": [],
        "bg_id": [],
        "cooks": [
            "4875"
        ],
        "set_price_on_sale": "0",
        "pic_url": "https://deltafoodpicture.sgp1.digitaloceanspaces.com/foods/1700291003151010.jpg"
    },
    {
        "f_id": 174813,
        "name": "ต้มยำกุ้ง",
        "pic_id": 103862,
        "price": 150,
        "detail": "ไม่ทราบ",
        "no_cook": "0",
        "sort": 32,
        "code_sale": "",
        "status": 2,
        "is_buffet": 0,
        "details": [],
        "code": "\t a032",
        "zone": [],
        "f_group": "12219",
        "toppings": [],
        "bg_id": [],
        "cooks": [
            "4875"
        ],
        "set_price_on_sale": "0",
        "pic_url": "https://deltafoodpicture.sgp1.digitaloceanspaces.com/foods/1700200987188711.jpg"
    },
    {
        "f_id": 174814,
        "name": "ต้มยำไก่",
        "pic_id": 104132,
        "price": 120,
        "detail": "ไม่ทราบ",
        "no_cook": "0",
        "sort": 33,
        "code_sale": "",
        "status": 2,
        "is_buffet": 0,
        "details": [],
        "code": "\t a033",
        "zone": [],
        "f_group": "12219",
        "toppings": [],
        "bg_id": [],
        "cooks": [
            "4875"
        ],
        "set_price_on_sale": "0",
        "pic_url": "https://deltafoodpicture.sgp1.digitaloceanspaces.com/foods/1700291306135967.jpg"
    },
    {
        "f_id": 174815,
        "name": "ต้มแซ่บกระดูกอ่อน",
        "pic_id": 104135,
        "price": 120,
        "detail": "ไม่ทราบ",
        "no_cook": "0",
        "sort": 34,
        "code_sale": "",
        "status": 2,
        "is_buffet": 0,
        "details": [],
        "code": "\t a034",
        "zone": [],
        "f_group": "12219",
        "toppings": [],
        "bg_id": [],
        "cooks": [
            "4875"
        ],
        "set_price_on_sale": "0",
        "pic_url": "https://deltafoodpicture.sgp1.digitaloceanspaces.com/foods/170029140871833.jpg"
    },
    {
        "f_id": 174816,
        "name": "แกงส้มชะอมกุ้ง",
        "pic_id": 103869,
        "price": 150,
        "detail": "ไม่ทราบ",
        "no_cook": "0",
        "sort": 35,
        "code_sale": "",
        "status": 2,
        "is_buffet": 0,
        "details": [],
        "code": "\t a035",
        "zone": [],
        "f_group": "12219",
        "toppings": [],
        "bg_id": [],
        "cooks": [
            "4875"
        ],
        "set_price_on_sale": "0",
        "pic_url": "https://deltafoodpicture.sgp1.digitaloceanspaces.com/foods/1700202504156821.jpg"
    },
    {
        "f_id": 174817,
        "name": "ไข่ตุ๋นทะเล",
        "pic_id": 104771,
        "price": 190,
        "detail": "ไม่ทราบ",
        "no_cook": "0",
        "sort": 36,
        "code_sale": "",
        "status": 2,
        "is_buffet": 0,
        "details": [],
        "code": "\t a036",
        "zone": [],
        "f_group": "12219",
        "toppings": [],
        "bg_id": [],
        "cooks": [
            "4875"
        ],
        "set_price_on_sale": "0",
        "pic_url": "https://deltafoodpicture.sgp1.digitaloceanspaces.com/foods/170071786767177.jpg"
    },
    {
        "f_id": 174818,
        "name": "ต้มยำขาหมูเผา",
        "pic_id": 103878,
        "price": 190,
        "detail": "ไม่ทราบ",
        "no_cook": "0",
        "sort": 37,
        "code_sale": "",
        "status": 2,
        "is_buffet": 0,
        "details": [],
        "code": "\t a037",
        "zone": [],
        "f_group": "12219",
        "toppings": [],
        "bg_id": [],
        "cooks": [
            "4875"
        ],
        "set_price_on_sale": "0",
        "pic_url": "https://deltafoodpicture.sgp1.digitaloceanspaces.com/foods/1700202735195364.jpg"
    },
    {
        "f_id": 174819,
        "name": "ยำแซลมอน",
        "pic_id": 103900,
        "price": 190,
        "detail": "ไม่ทราบ",
        "no_cook": "0",
        "sort": 38,
        "code_sale": "",
        "status": 2,
        "is_buffet": 0,
        "details": [],
        "code": "\t a038",
        "zone": [],
        "f_group": "12219",
        "toppings": [],
        "bg_id": [],
        "cooks": [
            "4875"
        ],
        "set_price_on_sale": "0",
        "pic_url": "https://deltafoodpicture.sgp1.digitaloceanspaces.com/foods/1700203470228523.jpg"
    },
    {
        "f_id": 174820,
        "name": "ยำปูอัดไข่กุ้ง",
        "pic_id": 104136,
        "price": 150,
        "detail": "ไม่ทราบ",
        "no_cook": "0",
        "sort": 39,
        "code_sale": "",
        "status": 2,
        "is_buffet": 0,
        "details": [],
        "code": "\t a039",
        "zone": [],
        "f_group": "12219",
        "toppings": [],
        "bg_id": [],
        "cooks": [
            "4875"
        ],
        "set_price_on_sale": "0",
        "pic_url": "https://deltafoodpicture.sgp1.digitaloceanspaces.com/foods/170029162988768.jpg"
    },
    {
        "f_id": 174821,
        "name": "ยำแซลมอนไข่กุ้ง",
        "pic_id": 104748,
        "price": 220,
        "detail": "ไม่ทราบ",
        "no_cook": "0",
        "sort": 40,
        "code_sale": "",
        "status": 2,
        "is_buffet": 0,
        "details": [],
        "code": "\t a040",
        "zone": [],
        "f_group": "12219",
        "toppings": [],
        "bg_id": [],
        "cooks": [
            "4875"
        ],
        "set_price_on_sale": "0",
        "pic_url": "https://deltafoodpicture.sgp1.digitaloceanspaces.com/foods/170071482046328.jpg"
    },
    {
        "f_id": 174822,
        "name": "ยำถั่วพลู",
        "pic_id": 104751,
        "price": 150,
        "detail": "ไม่ทราบ",
        "no_cook": "0",
        "sort": 41,
        "code_sale": "",
        "status": 2,
        "is_buffet": 0,
        "details": [],
        "code": "\t a041",
        "zone": [],
        "f_group": "12219",
        "toppings": [],
        "bg_id": [],
        "cooks": [
            "4875"
        ],
        "set_price_on_sale": "0",
        "pic_url": "https://deltafoodpicture.sgp1.digitaloceanspaces.com/foods/1700715420272005.jpg"
    },
    {
        "f_id": 174824,
        "name": "ยำไข่ดาว",
        "pic_id": 104137,
        "price": 120,
        "detail": "ไม่ทราบ",
        "no_cook": "0",
        "sort": 43,
        "code_sale": "",
        "status": 2,
        "is_buffet": 0,
        "details": [],
        "code": "\t a043",
        "zone": [],
        "f_group": "12219",
        "toppings": [],
        "bg_id": [],
        "cooks": [
            "4875"
        ],
        "set_price_on_sale": "0",
        "pic_url": "https://deltafoodpicture.sgp1.digitaloceanspaces.com/foods/1700291730199503.jpg"
    },
    {
        "f_id": 174825,
        "name": "ยำไข่มะตูม หมูสับ",
        "pic_id": 104149,
        "price": 120,
        "detail": "ไม่ทราบ",
        "no_cook": "0",
        "sort": 44,
        "code_sale": "",
        "status": 2,
        "is_buffet": 0,
        "details": [],
        "code": "\t a044",
        "zone": [],
        "f_group": "12219",
        "toppings": [],
        "bg_id": [],
        "cooks": [
            "4875"
        ],
        "set_price_on_sale": "0",
        "pic_url": "https://deltafoodpicture.sgp1.digitaloceanspaces.com/foods/1700293465163081.jpg"
    },
    {
        "f_id": 174826,
        "name": "ยำวุ้นเส้นหมูสับ ",
        "pic_id": 106808,
        "price": 150,
        "detail": "ไม่ทราบ",
        "no_cook": "0",
        "sort": 45,
        "code_sale": "",
        "status": 2,
        "is_buffet": 0,
        "details": [],
        "code": "\t a045",
        "zone": [],
        "f_group": "12219",
        "toppings": [],
        "bg_id": [],
        "cooks": [
            "4875"
        ],
        "set_price_on_sale": "0",
        "pic_url": "https://deltafoodpicture.sgp1.digitaloceanspaces.com/foods/1701865421146709.jpg"
    },
    {
        "f_id": 174827,
        "name": "ยำรวมมิตร",
        "pic_id": 104753,
        "price": 150,
        "detail": "ไม่ทราบ",
        "no_cook": "0",
        "sort": 46,
        "code_sale": "",
        "status": 2,
        "is_buffet": 0,
        "details": [],
        "code": "\t a046",
        "zone": [],
        "f_group": "12219",
        "toppings": [],
        "bg_id": [],
        "cooks": [
            "4875"
        ],
        "set_price_on_sale": "0",
        "pic_url": "https://deltafoodpicture.sgp1.digitaloceanspaces.com/foods/1700715645111493.jpg"
    },
    {
        "f_id": 174828,
        "name": "ยำหมูยอ",
        "pic_id": 104151,
        "price": 120,
        "detail": "ไม่ทราบ",
        "no_cook": "0",
        "sort": 47,
        "code_sale": "",
        "status": 2,
        "is_buffet": 0,
        "details": [],
        "code": "\t a047",
        "zone": [],
        "f_group": "12219",
        "toppings": [],
        "bg_id": [],
        "cooks": [
            "4875"
        ],
        "set_price_on_sale": "0",
        "pic_url": "https://deltafoodpicture.sgp1.digitaloceanspaces.com/foods/1700293599115960.jpg"
    },
    {
        "f_id": 174829,
        "name": "ยำไส้กรอก",
        "pic_id": 104152,
        "price": 120,
        "detail": "ไม่ทราบ",
        "no_cook": "0",
        "sort": 48,
        "code_sale": "",
        "status": 2,
        "is_buffet": 0,
        "details": [],
        "code": "\t a048",
        "zone": [],
        "f_group": "12219",
        "toppings": [],
        "bg_id": [],
        "cooks": [
            "4875"
        ],
        "set_price_on_sale": "0",
        "pic_url": "https://deltafoodpicture.sgp1.digitaloceanspaces.com/foods/170029373168205.jpg"
    },
    {
        "f_id": 174830,
        "name": "ยำทูน่า",
        "pic_id": 104153,
        "price": 150,
        "detail": "ไม่ทราบ",
        "no_cook": "0",
        "sort": 49,
        "code_sale": "",
        "status": 2,
        "is_buffet": 0,
        "details": [],
        "code": "\t a049",
        "zone": [],
        "f_group": "12219",
        "toppings": [],
        "bg_id": [],
        "cooks": [
            "4875"
        ],
        "set_price_on_sale": "0",
        "pic_url": "https://deltafoodpicture.sgp1.digitaloceanspaces.com/foods/1700293817145690.jpg"
    },
    {
        "f_id": 174831,
        "name": "ยำทะเล",
        "pic_id": 103916,
        "price": 190,
        "detail": "ไม่ทราบ",
        "no_cook": "0",
        "sort": 50,
        "code_sale": "",
        "status": 2,
        "is_buffet": 0,
        "details": [],
        "code": "\t a050",
        "zone": [],
        "f_group": "12219",
        "toppings": [],
        "bg_id": [],
        "cooks": [
            "4875"
        ],
        "set_price_on_sale": "0",
        "pic_url": "https://deltafoodpicture.sgp1.digitaloceanspaces.com/foods/1700204258257658.jpg"
    },
    {
        "f_id": 174832,
        "name": "กุ้งแช่น้ำปลา",
        "pic_id": 103863,
        "price": 190,
        "detail": "ไม่ทราบ",
        "no_cook": "0",
        "sort": 51,
        "code_sale": "",
        "status": 2,
        "is_buffet": 0,
        "details": [],
        "code": "\t a051",
        "zone": [],
        "f_group": "12219",
        "toppings": [],
        "bg_id": [],
        "cooks": [
            "4875"
        ],
        "set_price_on_sale": "0",
        "pic_url": "https://deltafoodpicture.sgp1.digitaloceanspaces.com/foods/1700201531199459.jpg"
    },
    {
        "f_id": 174833,
        "name": "ลาบหมู",
        "pic_id": 104156,
        "price": 120,
        "detail": "ไม่ทราบ",
        "no_cook": "0",
        "sort": 52,
        "code_sale": "",
        "status": 2,
        "is_buffet": 0,
        "details": [],
        "code": "\t a052",
        "zone": [],
        "f_group": "12219",
        "toppings": [],
        "bg_id": [],
        "cooks": [
            "4875"
        ],
        "set_price_on_sale": "0",
        "pic_url": "https://deltafoodpicture.sgp1.digitaloceanspaces.com/foods/1700294418423698.jpg"
    },
    {
        "f_id": 174835,
        "name": "ยำถั่วทอด",
        "pic_id": 104754,
        "price": 120,
        "detail": "ไม่ทราบ",
        "no_cook": "0",
        "sort": 53,
        "code_sale": "",
        "status": 2,
        "is_buffet": 0,
        "details": [],
        "code": "\t a053",
        "zone": [],
        "f_group": "12219",
        "toppings": [],
        "bg_id": [],
        "cooks": [
            "4875"
        ],
        "set_price_on_sale": "0",
        "pic_url": "https://deltafoodpicture.sgp1.digitaloceanspaces.com/foods/1700715756184001.jpg"
    },
    {
        "f_id": 174836,
        "name": "ยำไข่เยี่ยวม้า",
        "pic_id": 104158,
        "price": 120,
        "detail": "ไม่ทราบ",
        "no_cook": "0",
        "sort": 54,
        "code_sale": "",
        "status": 2,
        "is_buffet": 0,
        "details": [],
        "code": "\t a054",
        "zone": [],
        "f_group": "12219",
        "toppings": [],
        "bg_id": [],
        "cooks": [
            "4875"
        ],
        "set_price_on_sale": "0",
        "pic_url": "https://deltafoodpicture.sgp1.digitaloceanspaces.com/foods/170029464594197.jpg"
    },
    {
        "f_id": 174837,
        "name": "ยำสามกรอบ",
        "pic_id": 104157,
        "price": 150,
        "detail": "ไม่ทราบ",
        "no_cook": "0",
        "sort": 55,
        "code_sale": "",
        "status": 2,
        "is_buffet": 0,
        "details": [],
        "code": "\t a055",
        "zone": [],
        "f_group": "12219",
        "toppings": [],
        "bg_id": [],
        "cooks": [
            "4875"
        ],
        "set_price_on_sale": "0",
        "pic_url": "https://deltafoodpicture.sgp1.digitaloceanspaces.com/foods/1700294575104629.jpg"
    },
    {
        "f_id": 174838,
        "name": "หมูมะนาว",
        "pic_id": 104139,
        "price": 150,
        "detail": "ไม่ทราบ",
        "no_cook": "0",
        "sort": 56,
        "code_sale": "",
        "status": 2,
        "is_buffet": 0,
        "details": [],
        "code": "\t a056",
        "zone": [],
        "f_group": "12219",
        "toppings": [],
        "bg_id": [],
        "cooks": [
            "4875"
        ],
        "set_price_on_sale": "0",
        "pic_url": "https://deltafoodpicture.sgp1.digitaloceanspaces.com/foods/1700292466174158.jpg"
    },
    {
        "f_id": 174840,
        "name": "ตำปู ปลาร้า",
        "pic_id": 103861,
        "price": 79,
        "detail": "ไม่ทราบ",
        "no_cook": "0",
        "sort": 57,
        "code_sale": "",
        "status": 2,
        "is_buffet": 0,
        "details": [],
        "code": "\t a057",
        "zone": [],
        "f_group": "12219",
        "toppings": [],
        "bg_id": [],
        "cooks": [
            "4875"
        ],
        "set_price_on_sale": "0",
        "pic_url": "https://deltafoodpicture.sgp1.digitaloceanspaces.com/foods/1700200815203915.jpg"
    },
    {
        "f_id": 174841,
        "name": "ตำซั่ว",
        "pic_id": 103860,
        "price": 89,
        "detail": "ไม่ทราบ",
        "no_cook": "0",
        "sort": 58,
        "code_sale": "",
        "status": 0,
        "is_buffet": 0,
        "details": [],
        "code": "\t a058",
        "zone": [],
        "f_group": "12219",
        "toppings": [],
        "bg_id": [],
        "cooks": [
            "4875"
        ],
        "set_price_on_sale": "0",
        "pic_url": "https://deltafoodpicture.sgp1.digitaloceanspaces.com/foods/1700200703205015.jpg"
    },
    {
        "f_id": 174842,
        "name": "ตำไทย ใข่เค็ม",
        "pic_id": 104159,
        "price": 89,
        "detail": "ไม่ทราบ",
        "no_cook": "0",
        "sort": 59,
        "code_sale": "",
        "status": 2,
        "is_buffet": 0,
        "details": [],
        "code": "a059",
        "zone": [],
        "f_group": "12219",
        "toppings": [],
        "bg_id": [],
        "cooks": [
            "4875"
        ],
        "set_price_on_sale": "0",
        "pic_url": "https://deltafoodpicture.sgp1.digitaloceanspaces.com/foods/170029480486250.jpg"
    },
    {
        "f_id": 174844,
        "name": "ตำไทย",
        "pic_id": 104161,
        "price": 79,
        "detail": "ไม่ทราบ",
        "no_cook": "0",
        "sort": 60,
        "code_sale": "",
        "status": 2,
        "is_buffet": 0,
        "details": [],
        "code": "\t a060",
        "zone": [],
        "f_group": "12219",
        "toppings": [],
        "bg_id": [],
        "cooks": [
            "4875"
        ],
        "set_price_on_sale": "0",
        "pic_url": "https://deltafoodpicture.sgp1.digitaloceanspaces.com/foods/1700294881551416.jpg"
    },
    {
        "f_id": 174845,
        "name": "ตำแตง",
        "pic_id": 104162,
        "price": 89,
        "detail": "ไม่ทราบ",
        "no_cook": "0",
        "sort": 61,
        "code_sale": "",
        "status": 2,
        "is_buffet": 0,
        "details": [],
        "code": "\t a061",
        "zone": [],
        "f_group": "12219",
        "toppings": [],
        "bg_id": [],
        "cooks": [
            "4875"
        ],
        "set_price_on_sale": "0",
        "pic_url": "https://deltafoodpicture.sgp1.digitaloceanspaces.com/foods/170029492720309.jpg"
    },
    {
        "f_id": 174846,
        "name": "ตำข้าวโพด ใข่เค็ม",
        "pic_id": 103859,
        "price": 89,
        "detail": "ไม่ทราบ",
        "no_cook": "0",
        "sort": 62,
        "code_sale": "",
        "status": 2,
        "is_buffet": 0,
        "details": [],
        "code": "\t a062",
        "zone": [],
        "f_group": "12219",
        "toppings": [],
        "bg_id": [],
        "cooks": [
            "4875"
        ],
        "set_price_on_sale": "0",
        "pic_url": "https://deltafoodpicture.sgp1.digitaloceanspaces.com/foods/1700200550196497.jpg"
    },
    {
        "f_id": 174848,
        "name": "หมูแดดเดียว",
        "pic_id": 104163,
        "price": 140,
        "detail": "ไม่ทราบ",
        "no_cook": "0",
        "sort": 63,
        "code_sale": "",
        "status": 2,
        "is_buffet": 0,
        "details": [],
        "code": "\t a063",
        "zone": [],
        "f_group": "12219",
        "toppings": [],
        "bg_id": [],
        "cooks": [
            "4875"
        ],
        "set_price_on_sale": "0",
        "pic_url": "https://deltafoodpicture.sgp1.digitaloceanspaces.com/foods/1700295000401887.jpg"
    },
    {
        "f_id": 174849,
        "name": "เนื้อแดดเดียว",
        "pic_id": 104164,
        "price": 170,
        "detail": "ไม่ทราบ",
        "no_cook": "0",
        "sort": 64,
        "code_sale": "",
        "status": 2,
        "is_buffet": 0,
        "details": [],
        "code": "\t a064",
        "zone": [],
        "f_group": "12219",
        "toppings": [],
        "bg_id": [],
        "cooks": [
            "4875"
        ],
        "set_price_on_sale": "0",
        "pic_url": "https://deltafoodpicture.sgp1.digitaloceanspaces.com/foods/170029504153047.jpg"
    },
    {
        "f_id": 174850,
        "name": "ไก่ทอดเกลือ",
        "pic_id": 103864,
        "price": 140,
        "detail": "ไม่ทราบ",
        "no_cook": "0",
        "sort": 65,
        "code_sale": "",
        "status": 2,
        "is_buffet": 0,
        "details": [],
        "code": "\t a065",
        "zone": [],
        "f_group": "12219",
        "toppings": [],
        "bg_id": [],
        "cooks": [
            "4875"
        ],
        "set_price_on_sale": "0",
        "pic_url": "https://deltafoodpicture.sgp1.digitaloceanspaces.com/foods/1700201670242280.jpg"
    },
    {
        "f_id": 174852,
        "name": "เอ็นไก่ทอด",
        "pic_id": 104165,
        "price": 140,
        "detail": "ไม่ทราบ",
        "no_cook": "0",
        "sort": 66,
        "code_sale": "",
        "status": 2,
        "is_buffet": 0,
        "details": [],
        "code": "\t a066",
        "zone": [],
        "f_group": "12219",
        "toppings": [],
        "bg_id": [],
        "cooks": [
            "4875"
        ],
        "set_price_on_sale": "0",
        "pic_url": "https://deltafoodpicture.sgp1.digitaloceanspaces.com/foods/170029524056054.jpg"
    },
    {
        "f_id": 174853,
        "name": "สามชั้น ทอดน้ำปลา",
        "pic_id": 103915,
        "price": 140,
        "detail": "ไม่ทราบ",
        "no_cook": "0",
        "sort": 67,
        "code_sale": "",
        "status": 2,
        "is_buffet": 0,
        "details": [],
        "code": "\t a067",
        "zone": [],
        "f_group": "12219",
        "toppings": [],
        "bg_id": [],
        "cooks": [
            "4875"
        ],
        "set_price_on_sale": "0",
        "pic_url": "https://deltafoodpicture.sgp1.digitaloceanspaces.com/foods/1700204171313472.jpg"
    },
    {
        "f_id": 174854,
        "name": "ลาบหมูทอด",
        "pic_id": 104167,
        "price": 140,
        "detail": "ไม่ทราบ",
        "no_cook": "0",
        "sort": 68,
        "code_sale": "",
        "status": 2,
        "is_buffet": 0,
        "details": [],
        "code": "\t a068",
        "zone": [],
        "f_group": "12219",
        "toppings": [],
        "bg_id": [],
        "cooks": [
            "4875"
        ],
        "set_price_on_sale": "0",
        "pic_url": "https://deltafoodpicture.sgp1.digitaloceanspaces.com/foods/170029527495288.jpg"
    },
    {
        "f_id": 174855,
        "name": "กุ้งชุบแป้งทอด",
        "pic_id": 104168,
        "price": 190,
        "detail": "ไม่ทราบ",
        "no_cook": "0",
        "sort": 69,
        "code_sale": "",
        "status": 2,
        "is_buffet": 0,
        "details": [],
        "code": "\t a069",
        "zone": [],
        "f_group": "12219",
        "toppings": [],
        "bg_id": [],
        "cooks": [
            "4875"
        ],
        "set_price_on_sale": "0",
        "pic_url": "https://deltafoodpicture.sgp1.digitaloceanspaces.com/foods/1700295334120687.jpg"
    },
    {
        "f_id": 174856,
        "name": "ไข่เจียวหมูสับ",
        "pic_id": 104170,
        "price": 120,
        "detail": "ไม่ทราบ",
        "no_cook": "0",
        "sort": 70,
        "code_sale": "",
        "status": 2,
        "is_buffet": 0,
        "details": [],
        "code": "\t a070",
        "zone": [],
        "f_group": "12219",
        "toppings": [],
        "bg_id": [],
        "cooks": [
            "4875"
        ],
        "set_price_on_sale": "0",
        "pic_url": "https://deltafoodpicture.sgp1.digitaloceanspaces.com/foods/1700295442112683.jpg"
    },
    {
        "f_id": 174858,
        "name": "แหนมซี่โครงหมูทอด",
        "pic_id": 104172,
        "price": 150,
        "detail": "ไม่ทราบ",
        "no_cook": "0",
        "sort": 71,
        "code_sale": "",
        "status": 2,
        "is_buffet": 0,
        "details": [],
        "code": "\t a071",
        "zone": [],
        "f_group": "12219",
        "toppings": [],
        "bg_id": [],
        "cooks": [
            "4875"
        ],
        "set_price_on_sale": "0",
        "pic_url": "https://deltafoodpicture.sgp1.digitaloceanspaces.com/foods/170029563849848.jpg"
    },
    {
        "f_id": 174859,
        "name": "คอหมูทอดตะไคร้กรอบ",
        "pic_id": 103897,
        "price": 150,
        "detail": "ไม่ทราบ",
        "no_cook": "0",
        "sort": 72,
        "code_sale": "",
        "status": 2,
        "is_buffet": 0,
        "details": [],
        "code": "\t a072",
        "zone": [],
        "f_group": "12219",
        "toppings": [],
        "bg_id": [],
        "cooks": [
            "4875"
        ],
        "set_price_on_sale": "0",
        "pic_url": "https://deltafoodpicture.sgp1.digitaloceanspaces.com/foods/1700203174207571.jpg"
    },
    {
        "f_id": 174860,
        "name": "คอหมูย่าง",
        "pic_id": 104173,
        "price": 140,
        "detail": "ไม่ทราบ",
        "no_cook": "0",
        "sort": 73,
        "code_sale": "",
        "status": 2,
        "is_buffet": 0,
        "details": [],
        "code": "\t a073",
        "zone": [],
        "f_group": "12219",
        "toppings": [],
        "bg_id": [],
        "cooks": [
            "4875"
        ],
        "set_price_on_sale": "0",
        "pic_url": "https://deltafoodpicture.sgp1.digitaloceanspaces.com/foods/1700295688128537.jpg"
    },
    {
        "f_id": 174861,
        "name": "ข้าวผัดไข่ หมู",
        "pic_id": 104755,
        "price": 99,
        "detail": "ไม่ทราบ",
        "no_cook": "0",
        "sort": 74,
        "code_sale": "",
        "status": 2,
        "is_buffet": 0,
        "details": [],
        "code": "\t a074",
        "zone": [],
        "f_group": "12219",
        "toppings": [],
        "bg_id": [],
        "cooks": [
            "4875"
        ],
        "set_price_on_sale": "0",
        "pic_url": "https://deltafoodpicture.sgp1.digitaloceanspaces.com/foods/17007158091177984.jpg"
    },
    {
        "f_id": 174862,
        "name": "ข้าวผัดโบราณ",
        "pic_id": 104175,
        "price": 120,
        "detail": "ไม่ทราบ",
        "no_cook": "0",
        "sort": 75,
        "code_sale": "",
        "status": 2,
        "is_buffet": 0,
        "details": [],
        "code": "\t a075",
        "zone": [],
        "f_group": "12219",
        "toppings": [],
        "bg_id": [],
        "cooks": [
            "4875"
        ],
        "set_price_on_sale": "0",
        "pic_url": "https://deltafoodpicture.sgp1.digitaloceanspaces.com/foods/1700295860305255.jpg"
    },
    {
        "f_id": 174863,
        "name": "ข้าวผัดกุ้ง",
        "pic_id": 104176,
        "price": 150,
        "detail": "ไม่ทราบ",
        "no_cook": "0",
        "sort": 76,
        "code_sale": "",
        "status": 2,
        "is_buffet": 0,
        "details": [],
        "code": "\t a076",
        "zone": [],
        "f_group": "12219",
        "toppings": [],
        "bg_id": [],
        "cooks": [
            "4875"
        ],
        "set_price_on_sale": "0",
        "pic_url": "https://deltafoodpicture.sgp1.digitaloceanspaces.com/foods/1700295970192572.jpg"
    },
    {
        "f_id": 174864,
        "name": "ข้าวผัดทะเล",
        "pic_id": 104177,
        "price": 150,
        "detail": "ไม่ทราบ",
        "no_cook": "0",
        "sort": 77,
        "code_sale": "",
        "status": 2,
        "is_buffet": 0,
        "details": [],
        "code": "\t a077",
        "zone": [],
        "f_group": "12219",
        "toppings": [],
        "bg_id": [],
        "cooks": [
            "4875"
        ],
        "set_price_on_sale": "0",
        "pic_url": "https://deltafoodpicture.sgp1.digitaloceanspaces.com/foods/1700296082437461.jpg"
    },
    {
        "f_id": 174865,
        "name": "ข้าวผัดหมูกะเพราหมูคลุก",
        "pic_id": 104178,
        "price": 120,
        "detail": "ไม่ทราบ",
        "no_cook": "0",
        "sort": 78,
        "code_sale": "",
        "status": 2,
        "is_buffet": 0,
        "details": [],
        "code": "\t a078",
        "zone": [],
        "f_group": "12219",
        "toppings": [],
        "bg_id": [],
        "cooks": [
            "4875"
        ],
        "set_price_on_sale": "0",
        "pic_url": "https://deltafoodpicture.sgp1.digitaloceanspaces.com/foods/1700296193137197.jpg"
    },
    {
        "f_id": 174866,
        "name": "ข้าวต้มกุ้ง",
        "pic_id": 104179,
        "price": 120,
        "detail": "ไม่ทราบ",
        "no_cook": "0",
        "sort": 79,
        "code_sale": "",
        "status": 2,
        "is_buffet": 0,
        "details": [],
        "code": "\t a079",
        "zone": [],
        "f_group": "12219",
        "toppings": [],
        "bg_id": [],
        "cooks": [
            "4875"
        ],
        "set_price_on_sale": "0",
        "pic_url": "https://deltafoodpicture.sgp1.digitaloceanspaces.com/foods/170029625059523.jpg"
    },
    {
        "f_id": 174919,
        "name": "ข้าวผัดกะเพราปลาหมึก",
        "pic_id": 104180,
        "price": 149,
        "detail": "ไม่ทราบ",
        "no_cook": "0",
        "sort": 80,
        "code_sale": "",
        "status": 2,
        "is_buffet": 0,
        "details": [],
        "code": "\t a080",
        "zone": [],
        "f_group": "12219",
        "toppings": [],
        "bg_id": [],
        "cooks": [
            "4875"
        ],
        "set_price_on_sale": "0",
        "pic_url": "https://deltafoodpicture.sgp1.digitaloceanspaces.com/foods/1700296297212859.jpg"
    },
    {
        "f_id": 174920,
        "name": "ข้าวเปล่า",
        "pic_id": 104003,
        "price": 15,
        "detail": "ไม่ทราบ",
        "no_cook": "0",
        "sort": 81,
        "code_sale": "",
        "status": 2,
        "is_buffet": 0,
        "details": [],
        "code": "\t a081",
        "zone": [],
        "f_group": "12219",
        "toppings": [],
        "bg_id": [],
        "cooks": [
            "4875"
        ],
        "set_price_on_sale": "0",
        "pic_url": "https://deltafoodpicture.sgp1.digitaloceanspaces.com/foods/17002209218247.png"
    },
    {
        "f_id": 174921,
        "name": "ไข่ดาว",
        "pic_id": 103920,
        "price": 20,
        "detail": "ไม่ทราบ",
        "no_cook": "0",
        "sort": 82,
        "code_sale": "",
        "status": 2,
        "is_buffet": 0,
        "details": [],
        "code": "\t a082",
        "zone": [],
        "f_group": "12219",
        "toppings": [],
        "bg_id": [],
        "cooks": [
            "4875"
        ],
        "set_price_on_sale": "0",
        "pic_url": "https://deltafoodpicture.sgp1.digitaloceanspaces.com/foods/170020473635476.jpg"
    },
    {
        "f_id": 174922,
        "name": "ไข่ต้ม",
        "pic_id": 104002,
        "price": 20,
        "detail": "ไม่ทราบ",
        "no_cook": "0",
        "sort": 83,
        "code_sale": "",
        "status": 2,
        "is_buffet": 0,
        "details": [],
        "code": "\t a083",
        "zone": [],
        "f_group": "12219",
        "toppings": [],
        "bg_id": [],
        "cooks": [
            "4875"
        ],
        "set_price_on_sale": "0",
        "pic_url": "https://deltafoodpicture.sgp1.digitaloceanspaces.com/foods/1700220863147157.jpg"
    },
    {
        "f_id": 174923,
        "name": "แซลมอนซาซิมิ",
        "pic_id": 103899,
        "price": 250,
        "detail": "ไม่ทราบ",
        "no_cook": "0",
        "sort": 84,
        "code_sale": "",
        "status": 2,
        "is_buffet": 0,
        "details": [],
        "code": "\t a084",
        "zone": [],
        "f_group": "12219",
        "toppings": [],
        "bg_id": [],
        "cooks": [
            "4875"
        ],
        "set_price_on_sale": "0",
        "pic_url": "https://deltafoodpicture.sgp1.digitaloceanspaces.com/foods/1700203351192165.jpg"
    },
    {
        "f_id": 174924,
        "name": "ปูอัดซาซิมิ",
        "pic_id": 103999,
        "price": 120,
        "detail": "ไม่ทราบ",
        "no_cook": "0",
        "sort": 85,
        "code_sale": "",
        "status": 2,
        "is_buffet": 0,
        "details": [],
        "code": "\t a085",
        "zone": [],
        "f_group": "12219",
        "toppings": [],
        "bg_id": [],
        "cooks": [
            "4875"
        ],
        "set_price_on_sale": "0",
        "pic_url": "https://deltafoodpicture.sgp1.digitaloceanspaces.com/foods/1700220817356413.jpg"
    },
    {
        "f_id": 174925,
        "name": "ผลไม้รวม",
        "pic_id": 104756,
        "price": 150,
        "detail": "ไม่ทราบ",
        "no_cook": "0",
        "sort": 86,
        "code_sale": "",
        "status": 2,
        "is_buffet": 0,
        "details": [],
        "code": "\t a086",
        "zone": [],
        "f_group": "12219",
        "toppings": [],
        "bg_id": [],
        "cooks": [
            "4875"
        ],
        "set_price_on_sale": "0",
        "pic_url": "https://deltafoodpicture.sgp1.digitaloceanspaces.com/foods/1700715855180239.jpg"
    },
    {
        "f_id": 178690,
        "name": "ข้าวผัดกะเพราหมูกรอบ",
        "pic_id": 106017,
        "price": 120,
        "detail": "",
        "no_cook": "0",
        "sort": 126,
        "code_sale": "",
        "status": 2,
        "is_buffet": 0,
        "details": [],
        "code": "a087",
        "zone": [],
        "f_group": "12219",
        "toppings": [],
        "bg_id": [],
        "cooks": [
            "4875"
        ],
        "set_price_on_sale": "0",
        "pic_url": "https://deltafoodpicture.sgp1.digitaloceanspaces.com/foods/170133947862728.jpg"
    },
    {
        "f_id": 178693,
        "name": "ข้าวกะเพรากรอบเบคอน",
        "pic_id": 106142,
        "price": 129,
        "detail": "",
        "no_cook": "0",
        "sort": 127,
        "code_sale": "",
        "status": 2,
        "is_buffet": 0,
        "details": [],
        "code": "a088",
        "zone": [],
        "f_group": "12219",
        "toppings": [],
        "bg_id": [],
        "cooks": [
            "4875"
        ],
        "set_price_on_sale": "0",
        "pic_url": "https://deltafoodpicture.sgp1.digitaloceanspaces.com/foods/1701427864527212.jpg"
    },
    {
        "f_id": 178694,
        "name": "มาม่าต้มยำหมูกรอบน้ำข้น",
        "pic_id": 106741,
        "price": 150,
        "detail": "",
        "no_cook": "0",
        "sort": 128,
        "code_sale": "",
        "status": 2,
        "is_buffet": 0,
        "details": [],
        "code": "a089",
        "zone": [],
        "f_group": "12219",
        "toppings": [],
        "bg_id": [],
        "cooks": [
            "4875"
        ],
        "set_price_on_sale": "0",
        "pic_url": "https://deltafoodpicture.sgp1.digitaloceanspaces.com/foods/1701854724144835.jpg"
    },
    {
        "f_id": 178695,
        "name": "กะเพรากรอบเบคอน",
        "pic_id": 106722,
        "price": 250,
        "detail": "",
        "no_cook": "0",
        "sort": 129,
        "code_sale": "",
        "status": 2,
        "is_buffet": 0,
        "details": [],
        "code": "a090",
        "zone": [],
        "f_group": "12219",
        "toppings": [],
        "bg_id": [],
        "cooks": [
            "4875"
        ],
        "set_price_on_sale": "0",
        "pic_url": "https://deltafoodpicture.sgp1.digitaloceanspaces.com/foods/1701854103135764.jpg"
    },
    {
        "f_id": 178696,
        "name": "ยำหมูกรอบ",
        "pic_id": 106084,
        "price": 250,
        "detail": "",
        "no_cook": "0",
        "sort": 130,
        "code_sale": "",
        "status": 2,
        "is_buffet": 0,
        "details": [],
        "code": "a091",
        "zone": [],
        "f_group": "12219",
        "toppings": [],
        "bg_id": [],
        "cooks": [
            "4875"
        ],
        "set_price_on_sale": "0",
        "pic_url": "https://deltafoodpicture.sgp1.digitaloceanspaces.com/foods/1701417374150977.jpg"
    },
    {
        "f_id": 178711,
        "name": "ไข่ตุ๋นหมูสับ",
        "pic_id": 106135,
        "price": 150,
        "detail": "",
        "no_cook": "0",
        "sort": 133,
        "code_sale": "",
        "status": 2,
        "is_buffet": 0,
        "details": [],
        "code": "a092",
        "zone": [],
        "f_group": "12219",
        "toppings": [],
        "bg_id": [],
        "cooks": [
            "4875"
        ],
        "set_price_on_sale": "0",
        "pic_url": "https://deltafoodpicture.sgp1.digitaloceanspaces.com/foods/1701423838194098.jpg"
    },
    {
        "f_id": 180565,
        "name": "ยำวุ้นเส้นทะเล",
        "pic_id": 104752,
        "price": 190,
        "detail": "",
        "no_cook": "0",
        "sort": 169,
        "code_sale": "",
        "status": 2,
        "is_buffet": 0,
        "details": [],
        "code": "a093",
        "zone": [],
        "f_group": "12219",
        "toppings": [],
        "bg_id": [],
        "cooks": [
            "4875"
        ],
        "set_price_on_sale": "0",
        "pic_url": "https://deltafoodpicture.sgp1.digitaloceanspaces.com/foods/1700715475157014.jpg"
    },
    {
        "f_id": 182156,
        "name": "ข้าวผัดกะเพราหมู",
        "pic_id": 107766,
        "price": 99,
        "detail": "",
        "no_cook": "0",
        "sort": 199,
        "code_sale": "",
        "status": 2,
        "is_buffet": 0,
        "details": [],
        "code": "a094",
        "zone": [],
        "f_group": "12219",
        "toppings": [],
        "bg_id": [],
        "cooks": [
            "4875"
        ],
        "set_price_on_sale": "0",
        "pic_url": "https://deltafoodpicture.sgp1.digitaloceanspaces.com/foods/1702300945190564.jpg"
    },
    {
        "f_id": 182157,
        "name": "ข้าวผัดกะเพราไก่",
        "pic_id": 107768,
        "price": 99,
        "detail": "",
        "no_cook": "0",
        "sort": 200,
        "code_sale": "",
        "status": 2,
        "is_buffet": 0,
        "details": [],
        "code": "a095",
        "zone": [],
        "f_group": "12219",
        "toppings": [],
        "bg_id": [],
        "cooks": [
            "4875"
        ],
        "set_price_on_sale": "0",
        "pic_url": "https://deltafoodpicture.sgp1.digitaloceanspaces.com/foods/170230102050538.jpg"
    },
    {
        "f_id": 182334,
        "name": "ผัดกะเพราไก่",
        "pic_id": 107780,
        "price": 120,
        "detail": "",
        "no_cook": "0",
        "sort": 201,
        "code_sale": "",
        "status": 2,
        "is_buffet": 0,
        "details": [],
        "code": "a096",
        "zone": [],
        "f_group": "12219",
        "toppings": [],
        "bg_id": [],
        "cooks": [
            "4875"
        ],
        "set_price_on_sale": "0",
        "pic_url": "https://deltafoodpicture.sgp1.digitaloceanspaces.com/foods/170231886046608.jpg"
    },
    {
        "f_id": 182335,
        "name": "ผัดกะเพราทะเล",
        "pic_id": 107776,
        "price": 150,
        "detail": "",
        "no_cook": "0",
        "sort": 202,
        "code_sale": "",
        "status": 2,
        "is_buffet": 0,
        "details": [],
        "code": "a097",
        "zone": [],
        "f_group": "12219",
        "toppings": [],
        "bg_id": [],
        "cooks": [
            "4875"
        ],
        "set_price_on_sale": "0",
        "pic_url": "https://deltafoodpicture.sgp1.digitaloceanspaces.com/foods/170231862655020.jpg"
    },
    {
        "f_id": 182336,
        "name": "ผัดกะเพราปลาหมึก",
        "pic_id": 107778,
        "price": 150,
        "detail": "",
        "no_cook": "0",
        "sort": 203,
        "code_sale": "",
        "status": 2,
        "is_buffet": 0,
        "details": [],
        "code": "a098",
        "zone": [],
        "f_group": "12219",
        "toppings": [],
        "bg_id": [],
        "cooks": [
            "4875"
        ],
        "set_price_on_sale": "0",
        "pic_url": "https://deltafoodpicture.sgp1.digitaloceanspaces.com/foods/1702318644176725.jpg"
    },
    {
        "f_id": 182337,
        "name": "ผัดกะเพราหมูกรอบ",
        "pic_id": 107779,
        "price": 150,
        "detail": "",
        "no_cook": "0",
        "sort": 204,
        "code_sale": "",
        "status": 2,
        "is_buffet": 0,
        "details": [],
        "code": "a099",
        "zone": [],
        "f_group": "12219",
        "toppings": [],
        "bg_id": [],
        "cooks": [
            "4875"
        ],
        "set_price_on_sale": "0",
        "pic_url": "https://deltafoodpicture.sgp1.digitaloceanspaces.com/foods/1702318644294895.jpg"
    },
    {
        "f_id": 182338,
        "name": "ข้าวผัดไข่  ไก่",
        "pic_id": 104755,
        "price": 99,
        "detail": "",
        "no_cook": "0",
        "sort": 205,
        "code_sale": "",
        "status": 2,
        "is_buffet": 0,
        "details": [],
        "code": "a100",
        "zone": [],
        "f_group": "12219",
        "toppings": [],
        "bg_id": [],
        "cooks": [
            "4875"
        ],
        "set_price_on_sale": "0",
        "pic_url": "https://deltafoodpicture.sgp1.digitaloceanspaces.com/foods/17007158091177984.jpg"
    },
    {
        "f_id": 182339,
        "name": "ข้าวต้มหมู",
        "pic_id": 107781,
        "price": 100,
        "detail": "",
        "no_cook": "0",
        "sort": 206,
        "code_sale": "",
        "status": 2,
        "is_buffet": 0,
        "details": [],
        "code": "a101",
        "zone": [],
        "f_group": "12219",
        "toppings": [],
        "bg_id": [],
        "cooks": [
            "4875"
        ],
        "set_price_on_sale": "0",
        "pic_url": "https://deltafoodpicture.sgp1.digitaloceanspaces.com/foods/170231968791083.jpg"
    },
    {
        "f_id": 182341,
        "name": "ข้าวต้มไก่",
        "pic_id": 107782,
        "price": 100,
        "detail": "",
        "no_cook": "0",
        "sort": 207,
        "code_sale": "",
        "status": 2,
        "is_buffet": 0,
        "details": [],
        "code": "a102",
        "zone": [],
        "f_group": "12219",
        "toppings": [],
        "bg_id": [],
        "cooks": [
            "4875"
        ],
        "set_price_on_sale": "0",
        "pic_url": "https://deltafoodpicture.sgp1.digitaloceanspaces.com/foods/1702319721109481.jpg"
    },
    {
        "f_id": 182348,
        "name": "ป๊อปคอนรสออริจินัล",
        "pic_id": 103919,
        "price": 120,
        "detail": "",
        "no_cook": "0",
        "sort": 208,
        "code_sale": "",
        "status": 2,
        "is_buffet": 0,
        "details": [],
        "code": "a103",
        "zone": [],
        "f_group": "12219",
        "toppings": [],
        "bg_id": [],
        "cooks": [
            "4875"
        ],
        "set_price_on_sale": "0",
        "pic_url": "https://deltafoodpicture.sgp1.digitaloceanspaces.com/foods/1700204488213565.jpg"
    },
    {
        "f_id": 183641,
        "name": "มะนาวสไลค์",
        "pic_id": 108623,
        "price": 100,
        "detail": "",
        "no_cook": "0",
        "sort": 212,
        "code_sale": "",
        "status": 2,
        "is_buffet": 0,
        "details": [],
        "code": "a104",
        "zone": [],
        "f_group": "12219",
        "toppings": [],
        "bg_id": [],
        "cooks": [
            "4875"
        ],
        "set_price_on_sale": "0",
        "pic_url": "https://deltafoodpicture.sgp1.digitaloceanspaces.com/foods/17029874995816.jpg"
    },
    {
        "f_id": 185786,
        "name": "ถั่วทองการ์เด้น",
        "pic_id": 109516,
        "price": 100,
        "detail": "",
        "no_cook": "0",
        "sort": 235,
        "code_sale": "",
        "status": 2,
        "is_buffet": 0,
        "details": [],
        "code": "a105",
        "zone": [],
        "f_group": "12219",
        "toppings": [],
        "bg_id": [],
        "cooks": [
            "4756"
        ],
        "set_price_on_sale": "0",
        "pic_url": "https://deltafoodpicture.sgp1.digitaloceanspaces.com/foods/1703956988160824.jpg"
    },
    {
        "f_id": 189405,
        "name": "ชุดสแน็ค ",
        "pic_id": 111571,
        "price": 399,
        "detail": "",
        "no_cook": "0",
        "sort": 253,
        "code_sale": "",
        "status": 2,
        "is_buffet": 0,
        "details": [],
        "code": "a106",
        "zone": [],
        "f_group": "12219",
        "toppings": [],
        "bg_id": [],
        "cooks": [
            "4756"
        ],
        "set_price_on_sale": "0",
        "pic_url": "https://deltafoodpicture.sgp1.digitaloceanspaces.com/foods/1705170169133687.jpg"
    },
    {
        "f_id": 192203,
        "name": "แซลมอนราดซอสไข่กุ้ง",
        "pic_id": 114520,
        "price": 250,
        "detail": "",
        "no_cook": "0",
        "sort": 256,
        "code_sale": "",
        "status": 2,
        "is_buffet": 0,
        "details": [],
        "code": "A107",
        "zone": [],
        "f_group": "12219",
        "toppings": [],
        "bg_id": [],
        "cooks": [
            "4875"
        ],
        "set_price_on_sale": "0",
        "pic_url": "https://deltafoodpicture.sgp1.digitaloceanspaces.com/foods/1706186231190026.jpg"
    },
    {
        "f_id": 197864,
        "name": "น้ำตกคอหมูย่าง",
        "pic_id": 117510,
        "price": 120,
        "detail": "",
        "no_cook": "0",
        "sort": 258,
        "code_sale": "",
        "status": 2,
        "is_buffet": 0,
        "details": [],
        "code": "a108",
        "zone": [],
        "f_group": "12219",
        "toppings": [],
        "bg_id": [],
        "cooks": [
            "4875"
        ],
        "set_price_on_sale": "0",
        "pic_url": "https://deltafoodpicture.sgp1.digitaloceanspaces.com/foods/1707753537106360.jpg"
    },
    {
        "f_id": 197865,
        "name": "ผัดกะเพราหมูแดดเดียว",
        "pic_id": 117512,
        "price": 120,
        "detail": "",
        "no_cook": "0",
        "sort": 259,
        "code_sale": "",
        "status": 2,
        "is_buffet": 0,
        "details": [],
        "code": "a109",
        "zone": [],
        "f_group": "12219",
        "toppings": [],
        "bg_id": [],
        "cooks": [
            "4875"
        ],
        "set_price_on_sale": "0",
        "pic_url": "https://deltafoodpicture.sgp1.digitaloceanspaces.com/foods/170775432780456.jpg"
    },
    {
        "f_id": 197866,
        "name": "ผัดกะเพราเนื้อแดดเดียว",
        "pic_id": 117514,
        "price": 150,
        "detail": "",
        "no_cook": "0",
        "sort": 260,
        "code_sale": "",
        "status": 2,
        "is_buffet": 0,
        "details": [],
        "code": "a110",
        "zone": [],
        "f_group": "12219",
        "toppings": [],
        "bg_id": [],
        "cooks": [
            "4875"
        ],
        "set_price_on_sale": "0",
        "pic_url": "https://deltafoodpicture.sgp1.digitaloceanspaces.com/foods/170775455280532.jpg"
    },
    {
        "f_id": 197867,
        "name": "ข้าวผัดกะเพราหมูแดดเดียว",
        "pic_id": 117511,
        "price": 120,
        "detail": "",
        "no_cook": "0",
        "sort": 261,
        "code_sale": "",
        "status": 2,
        "is_buffet": 0,
        "details": [],
        "code": "a111",
        "zone": [],
        "f_group": "12219",
        "toppings": [],
        "bg_id": [],
        "cooks": [
            "4875"
        ],
        "set_price_on_sale": "0",
        "pic_url": "https://deltafoodpicture.sgp1.digitaloceanspaces.com/foods/170775398986482.jpg"
    },
    {
        "f_id": 197868,
        "name": "ข้าวผัดกะเพราเนื้อแดดเดียว",
        "pic_id": 117513,
        "price": 150,
        "detail": "",
        "no_cook": "0",
        "sort": 262,
        "code_sale": "",
        "status": 2,
        "is_buffet": 0,
        "details": [],
        "code": "a112",
        "zone": [],
        "f_group": "12219",
        "toppings": [],
        "bg_id": [],
        "cooks": [
            "4875"
        ],
        "set_price_on_sale": "0",
        "pic_url": "https://deltafoodpicture.sgp1.digitaloceanspaces.com/foods/170775444464539.jpg"
    }
]